setup.cfg
setup.py
afp_cli/__init__.py
afp_cli/aws_credentials_file.py
afp_cli/cli.py
afp_cli/cli_functions.py
afp_cli/client.py
afp_cli/cliv2.py
afp_cli/compat.py
afp_cli/config.py
afp_cli/exporters.py
afp_cli/log.py
afp_cli/password_providers.py
afp_cli.egg-info/PKG-INFO
afp_cli.egg-info/SOURCES.txt
afp_cli.egg-info/dependency_links.txt
afp_cli.egg-info/entry_points.txt
afp_cli.egg-info/namespace_packages.txt
afp_cli.egg-info/requires.txt
afp_cli.egg-info/top_level.txt
afp_cli.egg-info/zip-safe
scripts/afp
scripts/afpv2