Metadata-Version: 1.1
Name: afp-cli
Version: 370.315
Summary: Command line client for AWS federation proxy api
Home-page: https://github.com/ImmobilienScout24/afp-cli
Author: Stefan Neben, Tobias Vollmer, Stefan Nordhausen, Enrico Heine, Valentin Haenel
Author-email: stefan.neben@immobilienscout24.de, tobias.vollmer@immobilienscout24.de, stefan.nordhausen@immobilienscout24.de, enrico.heine@immobilienscout24.de, valentin.haenel@immobilienscout24.de
License: Apache License 2.0
Platform: UNKNOWN
Classifier: Programming Language :: Python
Classifier: Programming Language :: Python :: 2
Classifier: Programming Language :: Python :: 2.6
Classifier: Programming Language :: Python :: 2.7
Classifier: Programming Language :: Python :: 3
Classifier: Programming Language :: Python :: 3.3
Classifier: Programming Language :: Python :: 3.4
Classifier: Programming Language :: Python :: 3.5
Classifier: Programming Language :: Python :: 3.6
